agentfleet/__init__.py
agentfleet/agent.py
agentfleet/chatroom.py
agentfleet/mytools.py
agentfleet-0.1.4.dist-info/METADATA
agentfleet-0.1.4.dist-info/WHEEL
agentfleet-0.1.4.dist-info/top_level.txt
agentfleet-0.1.4.dist-info/RECORD
