Metadata-Version: 2.4
Name: agentfleet
Version: 0.1.4
Summary: A package for managing AI agents and chatrooms
Author: Wei Zhou
Classifier: Programming Language :: Python :: 3
Classifier: License :: OSI Approved :: MIT License
Classifier: Operating System :: OS Independent
Requires-Python: >=3.6
Requires-Dist: langchain
Requires-Dist: langchain-openai
Requires-Dist: langchain-community
Requires-Dist: langchain-deepseek
Requires-Dist: pydantic
Requires-Dist: pyjwt
Dynamic: author
Dynamic: classifier
Dynamic: description
Dynamic: description-content-type
Dynamic: requires-dist
Dynamic: requires-python
Dynamic: summary
